LeCatchu/README.md
LeCatchu/__init__.py
LeCatchu/main.py
lecatchu-9.0.0.dist-info/METADATA
lecatchu-9.0.0.dist-info/WHEEL
lecatchu-9.0.0.dist-info/RECORD
