Metadata-Version: 2.4
Name: LeCatchu
Version: 9.0.0
Summary: LeCatchu - Powerful and Light-weight Cryptography Engine
Project-URL: Homepage, https://github.com/aertsimon90/LeCatchu
Project-URL: Repository, https://github.com/aertsimon90/LeCatchu
Author-email: Simon Scap <simon.scap090@gmail.com>
License: MIT
Keywords: cryptography
Classifier: License :: OSI Approved :: MIT License
Classifier: Operating System :: OS Independent
Classifier: Programming Language :: Python :: 3
Requires-Python: >=3.8
